daeclipse/.gitignore
daeclipse/__init__.py
daeclipse/api.py
daeclipse/models/__init__.py
daeclipse/models/collection.py
daeclipse/models/collectioninfo.py
daeclipse/models/comment.py
daeclipse/models/commentcontent.py
daeclipse/models/commentslist.py
daeclipse/models/deviation.py
daeclipse/models/deviationawardedbadge.py
daeclipse/models/deviationextended.py
daeclipse/models/deviationextendedcontent.py
daeclipse/models/deviationextendedresult.py
daeclipse/models/deviationextendedstats.py
daeclipse/models/deviationfilespecs.py
daeclipse/models/deviationmedia.py
daeclipse/models/deviationrelatedstreams.py
daeclipse/models/deviationtag.py
daeclipse/models/deviationtypefacet.py
daeclipse/models/folder.py
daeclipse/models/groupslist.py
daeclipse/models/gruser.py
daeclipse/models/model.py
daeclipse/models/stats.py
daeclipse/models/usercomment.py
daeclipse/models/userscommentslist.py
daeclipse-0.1.0.dist-info/LICENSE
daeclipse-0.1.0.dist-info/WHEEL
daeclipse-0.1.0.dist-info/METADATA
daeclipse-0.1.0.dist-info/RECORD
