Metadata-Version: 2.1
Name: daeclipse
Version: 0.1.0
Summary: A Python library for DeviantArt Eclipse functionality
Home-page: https://kathryndipippo.com/daeclipse/
License: MIT
Keywords: python,deviantart
Author: Kathryn DiPippo
Author-email: dipippo.k@gmail.com
Requires-Python: >=3.7,<4.0.0
Classifier: License :: OSI Approved :: MIT License
Classifier: Programming Language :: Python :: 3
Classifier: Programming Language :: Python :: 3.7
Classifier: Programming Language :: Python :: 3.8
Classifier: Programming Language :: Python :: 3.9
Requires-Dist: beautifulsoup4 (>=4.7.1,<5.0.0)
Requires-Dist: browser-cookie3 (>=0.12.1,<0.13.0)
Requires-Dist: cli-ui (>=0.14.1,<0.16.0)
Requires-Dist: html-to-draftjs (>=1.0.1,<2.0.0)
Requires-Dist: pick (>=1.0.0,<2.0.0)
Requires-Dist: python-dotenv (>=0.19.0,<0.20.0)
Requires-Dist: requests (>=2.26.0,<3.0.0)
Requires-Dist: tabulate (>=0.8.9,<0.9.0)
Requires-Dist: typer (>=0.3.2,<0.4.0)
Project-URL: Issues, https://github.com/Pepper-Wood/daeclipse/issues
Project-URL: Repository, https://github.com/Pepper-Wood/daeclipse
